fractalinator/__init__.py
fractalinator/artwork.py
fractalinator/tkapp.py
fractalinator/util.py
fractalinator-1.0.1.dist-info/METADATA
fractalinator-1.0.1.dist-info/WHEEL
fractalinator-1.0.1.dist-info/top_level.txt
fractalinator-1.0.1.dist-info/RECORD
